utoken/__init__.py
utoken/__main__.py
utoken/detokenize.py
utoken/util.py
utoken/utokenize.py
utoken/data/detok-resource.txt
utoken/data/tok-resource-amh.txt
utoken/data/tok-resource-ara.txt
utoken/data/tok-resource-asm.txt
utoken/data/tok-resource-ben.txt
utoken/data/tok-resource-bul.txt
utoken/data/tok-resource-cat.txt
utoken/data/tok-resource-ces.txt
utoken/data/tok-resource-cym.txt
utoken/data/tok-resource-dan.txt
utoken/data/tok-resource-deu.txt
utoken/data/tok-resource-ecg.txt
utoken/data/tok-resource-ell.txt
utoken/data/tok-resource-eng-global.txt
utoken/data/tok-resource-eng.txt
utoken/data/tok-resource-est.txt
utoken/data/tok-resource-fas.txt
utoken/data/tok-resource-fin.txt
utoken/data/tok-resource-fra.txt
utoken/data/tok-resource-gle.txt
utoken/data/tok-resource-grc.txt
utoken/data/tok-resource-guj.txt
utoken/data/tok-resource-hbo.txt
utoken/data/tok-resource-heb.txt
utoken/data/tok-resource-hin.txt
utoken/data/tok-resource-hun.txt
utoken/data/tok-resource-hye.txt
utoken/data/tok-resource-ind.txt
utoken/data/tok-resource-isl.txt
utoken/data/tok-resource-ita.txt
utoken/data/tok-resource-kan.txt
utoken/data/tok-resource-kat.txt
utoken/data/tok-resource-kaz.txt
utoken/data/tok-resource-kor.txt
utoken/data/tok-resource-lao.txt
utoken/data/tok-resource-lav.txt
utoken/data/tok-resource-lit.txt
utoken/data/tok-resource-mal.txt
utoken/data/tok-resource-mar.txt
utoken/data/tok-resource-mkd.txt
utoken/data/tok-resource-mni.txt
utoken/data/tok-resource-nld.txt
utoken/data/tok-resource-nor.txt
utoken/data/tok-resource-ori.txt
utoken/data/tok-resource-pan.txt
utoken/data/tok-resource-pol.txt
utoken/data/tok-resource-por.txt
utoken/data/tok-resource-pus.txt
utoken/data/tok-resource-que.txt
utoken/data/tok-resource-ron.txt
utoken/data/tok-resource-rus.txt
utoken/data/tok-resource-sin.txt
utoken/data/tok-resource-slk.txt
utoken/data/tok-resource-slv.txt
utoken/data/tok-resource-som.txt
utoken/data/tok-resource-spa.txt
utoken/data/tok-resource-swa.txt
utoken-0.1.8.dist-info/LICENSE
utoken-0.1.8.dist-info/METADATA
utoken-0.1.8.dist-info/WHEEL
utoken-0.1.8.dist-info/entry_points.txt
utoken-0.1.8.dist-info/top_level.txt
utoken-0.1.8.dist-info/RECORD
