Metadata-Version: 2.1
Name: utoken
Version: 0.1.8
Summary: utoken is a universal tokenizer (multilingual word segmenter) that divides text into words, punctuation and special tokens such as numbers, URLs, XML tags, email-addresses and hashtags. It comes with a companion detokenizer.
Home-page: https://github.com/uhermjakob/utoken
Author: Ulf Hermjakob
Author-email: ulf@isi.edu
License: UNKNOWN
Download-URL: https://github.com/uhermjakob/utoken
Keywords: machine translation,datasets,NLP,natural language processing,computational linguistics
Platform: any
Classifier: Development Status :: 5 - Production/Stable
Classifier: Intended Audience :: Developers
Classifier: Topic :: Utilities
Classifier: Topic :: Text Processing
Classifier: Topic :: Text Processing :: General
Classifier: Topic :: Text Processing :: Filters
Classifier: Topic :: Text Processing :: Linguistic
Classifier: License :: OSI Approved :: Apache Software License
Classifier: Programming Language :: Python :: 3 :: Only
Requires-Python: >=3.8
Requires-Dist: regex (==2021.8.3)
